silabs_rps/__init__.py
silabs_rps/rps_convert.py
silabs_rps/rps_create.py
silabs_rps/rps/__init__.py
silabs_rps/rps_checksum/__init__.py
silabs_rps/rps_consts/__init__.py
silabs_rps/rps_crc/__init__.py
silabs_rps/rps_crypto/__init__.py
silabs_rps/rps_helpers/__init__.py
silabs_rps-1.2.0.dist-info/METADATA
silabs_rps-1.2.0.dist-info/WHEEL
silabs_rps-1.2.0.dist-info/entry_points.txt
silabs_rps-1.2.0.dist-info/licenses/LICENSE.md
silabs_rps-1.2.0.dist-info/RECORD
