Metadata-Version: 2.4
Name: silabs-rps
Version: 1.2.0
Summary: Silicon Labs RPS Image Creation and Conversion Tools
Project-URL: Homepage, https://github.com/SiliconLabsSoftware/utils-rps
Author: Silicon Labs
License-Expression: LicenseRef-MSLA
License-File: LICENSE.md
Requires-Python: >=3.10
Requires-Dist: intelhex
Requires-Dist: pycryptodome
